{
  "date": "2026-06-21",
  "fetched_at": "2026-06-21T11:10:39.262820+00:00",
  "source": "the_odds_api_live",
  "games": [
    {
      "home_team": "Atlanta Braves",
      "away_team": "Milwaukee Brewers",
      "commence_time": "2026-06-21T17:36:00Z",
      "home_ml": -130,
      "away_ml": 110,
      "ou_line": 8.5,
      "over_odds": -119,
      "under_odds": -103,
      "home_spread_point": -1.5,
      "home_spread_american": 150,
      "away_spread_point": 1.5,
      "away_spread_american": -178
    },
    {
      "home_team": "New York Yankees",
      "away_team": "Cincinnati Reds",
      "commence_time": "2026-06-21T17:36:00Z",
      "home_ml": -110,
      "away_ml": -105,
      "ou_line": 8.5,
      "over_odds": -105,
      "under_odds": -115,
      "home_spread_point": 1.5,
      "home_spread_american": -180,
      "away_spread_point": -1.5,
      "away_spread_american": 150
    },
    {
      "home_team": "Detroit Tigers",
      "away_team": "Chicago White Sox",
      "commence_time": "2026-06-21T17:41:00Z",
      "home_ml": -117,
      "away_ml": -101,
      "ou_line": 8.0,
      "over_odds": -115,
      "under_odds": -105,
      "home_spread_point": 1.5,
      "home_spread_american": -192,
      "away_spread_point": -1.5,
      "away_spread_american": 158
    },
    {
      "home_team": "Miami Marlins",
      "away_team": "San Francisco Giants",
      "commence_time": "2026-06-21T17:41:00Z",
      "home_ml": 123,
      "away_ml": -144,
      "ou_line": 7.5,
      "over_odds": -120,
      "under_odds": 100,
      "home_spread_point": 1.5,
      "home_spread_american": -142,
      "away_spread_point": -1.5,
      "away_spread_american": 120
    },
    {
      "home_team": "Tampa Bay Rays",
      "away_team": "Washington Nationals",
      "commence_time": "2026-06-21T17:41:00Z",
      "home_ml": -135,
      "away_ml": 116,
      "ou_line": 8.0,
      "over_odds": -115,
      "under_odds": -105,
      "home_spread_point": -1.5,
      "home_spread_american": 156,
      "away_spread_point": 1.5,
      "away_spread_american": -185
    },
    {
      "home_team": "Houston Astros",
      "away_team": "Cleveland Guardians",
      "commence_time": "2026-06-21T18:11:00Z",
      "home_ml": -133,
      "away_ml": 115,
      "ou_line": 8.5,
      "over_odds": -120,
      "under_odds": 100,
      "home_spread_point": -1.5,
      "home_spread_american": 150,
      "away_spread_point": 1.5,
      "away_spread_american": -180
    },
    {
      "home_team": "Kansas City Royals",
      "away_team": "St. Louis Cardinals",
      "commence_time": "2026-06-21T18:11:00Z",
      "home_ml": 105,
      "away_ml": -125,
      "ou_line": 9.0,
      "over_odds": -115,
      "under_odds": -105,
      "home_spread_point": 1.5,
      "home_spread_american": -155,
      "away_spread_point": -1.5,
      "away_spread_american": 130
    },
    {
      "home_team": "Chicago Cubs",
      "away_team": "Toronto Blue Jays",
      "commence_time": "2026-06-21T18:21:00Z",
      "home_ml": 104,
      "away_ml": -121,
      "ou_line": 6.5,
      "over_odds": -118,
      "under_odds": -102,
      "home_spread_point": 1.5,
      "home_spread_american": -174,
      "away_spread_point": -1.5,
      "away_spread_american": 145
    },
    {
      "home_team": "Texas Rangers",
      "away_team": "San Diego Padres",
      "commence_time": "2026-06-21T18:36:00Z",
      "home_ml": -147,
      "away_ml": 124,
      "ou_line": 7.5,
      "over_odds": -110,
      "under_odds": -110,
      "home_spread_point": -1.5,
      "home_spread_american": 150,
      "away_spread_point": 1.5,
      "away_spread_american": -179
    },
    {
      "home_team": "Colorado Rockies",
      "away_team": "Pittsburgh Pirates",
      "commence_time": "2026-06-21T19:11:00Z",
      "home_ml": 123,
      "away_ml": -145,
      "ou_line": 12.0,
      "over_odds": -105,
      "under_odds": -115,
      "home_spread_point": 1.5,
      "home_spread_american": -125,
      "away_spread_point": -1.5,
      "away_spread_american": 105
    },
    {
      "home_team": "Athletics",
      "away_team": "Los Angeles Angels",
      "commence_time": "2026-06-21T20:06:00Z",
      "home_ml": -126,
      "away_ml": 108,
      "ou_line": 9.5,
      "over_odds": -105,
      "under_odds": -115,
      "home_spread_point": -1.5,
      "home_spread_american": 149,
      "away_spread_point": 1.5,
      "away_spread_american": -175
    },
    {
      "home_team": "Los Angeles Dodgers",
      "away_team": "Baltimore Orioles",
      "commence_time": "2026-06-21T20:11:00Z",
      "home_ml": -215,
      "away_ml": 180,
      "ou_line": 9.0,
      "over_odds": -110,
      "under_odds": -110,
      "home_spread_point": -1.5,
      "home_spread_american": -104,
      "away_spread_point": 1.5,
      "away_spread_american": -115
    },
    {
      "home_team": "Seattle Mariners",
      "away_team": "Boston Red Sox",
      "commence_time": "2026-06-21T20:11:00Z",
      "home_ml": -142,
      "away_ml": 120,
      "ou_line": 6.5,
      "over_odds": -115,
      "under_odds": -105,
      "home_spread_point": -1.5,
      "home_spread_american": 157,
      "away_spread_point": 1.5,
      "away_spread_american": -188
    },
    {
      "home_team": "Philadelphia Phillies",
      "away_team": "New York Mets",
      "commence_time": "2026-06-21T23:21:00Z",
      "home_ml": -196,
      "away_ml": 166,
      "ou_line": 8.0,
      "over_odds": -112,
      "under_odds": -106,
      "home_spread_point": -1.5,
      "home_spread_american": 110,
      "away_spread_point": 1.5,
      "away_spread_american": -130
    }
  ]
}